[
  {
    "id": "68bf4e06214d3b4d",
    "product_id": "1password",
    "product_name": "1Password",
    "icon_url": "https://www.google.com/s2/favicons?domain=1password.com&sz=64",
    "title": "1Password for Android Beta",
    "link": "https://releases.1password.com/",
    "summary": "All Mac iOS",
    "date": "March 25 2026"
  },
  {
    "id": "9c09b21f403ecfc4",
    "product_id": "1password",
    "product_name": "1Password",
    "icon_url": "https://www.google.com/s2/favicons?domain=1password.com&sz=64",
    "title": "1Password works everywhereMac iOS Windows Android Browser Linux Developer tools Provisioning",
    "link": "https://releases.1password.com/mac/",
    "summary": "",
    "date": "2026-03-06T17:53:53.055734+00:00"
  },
  {
    "id": "42a3f8f87b22f5a9",
    "product_id": "ad-astra",
    "product_name": "Ad Astra",
    "icon_url": "https://www.google.com/s2/favicons?domain=aais.com&sz=64",
    "title": "March 27, 2026",
    "link": "https://help.adastra.live/hc/en-us/articles/47657628557716-March-27-2026",
    "summary": "",
    "date": "2026-03-31T14:02:45Z"
  },
  {
    "id": "6c69a5955f64668a",
    "product_id": "ad-astra",
    "product_name": "Ad Astra",
    "icon_url": "https://www.google.com/s2/favicons?domain=aais.com&sz=64",
    "title": "March 20, 2026",
    "link": "https://help.adastra.live/hc/en-us/articles/47415183812244-March-20-2026",
    "summary": "",
    "date": "2026-03-20T16:17:05Z"
  },
  {
    "id": "3218f8844f70fc26",
    "product_id": "ad-astra",
    "product_name": "Ad Astra",
    "icon_url": "https://www.google.com/s2/favicons?domain=aais.com&sz=64",
    "title": "March 13, 2026",
    "link": "https://help.adastra.live/hc/en-us/articles/47265807993492-March-13-2026",
    "summary": "",
    "date": "2026-03-16T15:49:25Z"
  },
  {
    "id": "c92b503e4e43b907",
    "product_id": "ad-astra",
    "product_name": "Ad Astra",
    "icon_url": "https://www.google.com/s2/favicons?domain=aais.com&sz=64",
    "title": "March 6, 2026",
    "link": "https://help.adastra.live/hc/en-us/articles/46950677019668-March-6-2026",
    "summary": "",
    "date": "2026-03-06T18:13:10Z"
  },
  {
    "id": "f54aa9f1968974da",
    "product_id": "ad-astra",
    "product_name": "Ad Astra",
    "icon_url": "https://www.google.com/s2/favicons?domain=aais.com&sz=64",
    "title": "February 27, 2026",
    "link": "https://help.adastra.live/hc/en-us/articles/46722487093396-February-27-2026",
    "summary": "",
    "date": "2026-02-27T20:36:01Z"
  },
  {
    "id": "8e642c0b32a90b7c",
    "product_id": "canva",
    "product_name": "Canva",
    "icon_url": "https://www.google.com/s2/favicons?domain=canva.com&sz=64",
    "title": "A new type request parameter has been added to the Create design API. Although this type is shown as required, for backward compatibility, if it isn't",
    "link": "https://www.canva.dev/docs/connect/api-reference/designs/create-design/",
    "summary": "A new type request parameter has been added to the Create design API. Although this type is shown as required, for backward compatibility, if it isn't provided in a request, the request type will be assumed to be type_and_asset.",
    "date": "2026-03-29T23:47:59.875578+00:00"
  },
  {
    "id": "eb2eaea6cca0fce1",
    "product_id": "canva",
    "product_name": "Canva",
    "icon_url": "https://www.google.com/s2/favicons?domain=canva.com&sz=64",
    "title": "The Create design autofill job API now supports column_configs for chart data fields, allowing you to define column names and data types separately f",
    "link": "https://www.canva.dev/docs/connect/api-reference/autofills/create-design-autofill-job/",
    "summary": "The Create design autofill job API now supports column_configs for chart data fields, allowing you to define column names and data types separately from your data.",
    "date": "2026-03-29T23:47:59.875601+00:00"
  },
  {
    "id": "dd3c1c79dc975c71",
    "product_id": "canva",
    "product_name": "Canva",
    "icon_url": "https://www.google.com/s2/favicons?domain=canva.com&sz=64",
    "title": "The Create design export job API now supports two additional email export formats: html_bundle and html_standalone. Use these formats when creating e",
    "link": "https://www.canva.dev/docs/connect/api-reference/exports/create-design-export-job/",
    "summary": "The Create design export job API now supports two additional email export formats: html_bundle and html_standalone. Use these formats when creating export jobs for email designs, depending on whether you need bundled assets (html_bundle) or a standalone HTML output (html_standalone).",
    "date": "2026-03-29T23:47:59.875608+00:00"
  },
  {
    "id": "54f24d9fe9316d8b",
    "product_id": "canva",
    "product_name": "Canva",
    "icon_url": "https://www.google.com/s2/favicons?domain=canva.com&sz=64",
    "title": "The Assets APIs⁠(opens in a new tab or window) now return an additional metadata property as part of the asset object.",
    "link": "https://www.canva.dev/docs/connect/api-reference/assets/",
    "summary": "",
    "date": "2026-03-29T23:47:59.875627+00:00"
  },
  {
    "id": "6077feb66c340f69",
    "product_id": "canva",
    "product_name": "Canva",
    "icon_url": "https://www.google.com/s2/favicons?domain=canva.com&sz=64",
    "title": "The List folder items API now supports a pin_status parameter to filter for pinned items in a folder.",
    "link": "https://www.canva.dev/docs/connect/api-reference/folders/list-folder-items/",
    "summary": "",
    "date": "2026-03-06T17:53:56.012065+00:00"
  },
  {
    "id": "2aa25658903bd41b",
    "product_id": "clickup",
    "product_name": "ClickUp",
    "icon_url": "https://www.google.com/s2/favicons?domain=clickup.com&sz=64",
    "title": "Release Notes 4.02",
    "link": "https://feedback.clickup.com/changelog/release-notes-402",
    "summary": "Update Task Types in Views, Pin AI Notetaker, and more! This week’s release unlocks the ability to manage Task Types in Views, add date ranges to Gantt view exports, and so much more. Update Task Type Column in Your Views: Quickly see and update task types directly from your List and Table views....",
    "date": "2026-02-24T18:20:19+00:00"
  },
  {
    "id": "f014c68f141a3a26",
    "product_id": "clickup",
    "product_name": "ClickUp",
    "icon_url": "https://www.google.com/s2/favicons?domain=clickup.com&sz=64",
    "title": "Super Agents: Release Notes Takeover",
    "link": "https://feedback.clickup.com/changelog/super-agents-release-notes-takeover",
    "summary": "Super Agents: The world's first human-like AI AgentsSuper Agents™ are personalized AI teammates that understand your work, use powerful tools, and collaborate like humans. Just describe the problem you want solved, the workflow you want to automate, or where you’re wasting time, and Super Agents...",
    "date": "2026-01-29T18:19:37+00:00"
  },
  {
    "id": "9e6059223bff720f",
    "product_id": "clickup",
    "product_name": "ClickUp",
    "icon_url": "https://www.google.com/s2/favicons?domain=clickup.com&sz=64",
    "title": "⚡ Join us for a Super Agents AMA on Reddit!",
    "link": "https://feedback.clickup.com/changelog/join-us-for-a-super-agents-ama-on-reddit",
    "summary": "Hey, everyone!We’re excited to announce a special Reddit AMA (Ask Me Anything) with the ClickUp AI Team, all about our latest feature: Super Agents!🗓️ When: Thursday, January 22nd, 10am–12pm PST📍 Where: the r/ClickUp subreddit on RedditThis is your opportunity to connect directly with Michael Van...",
    "date": "2026-01-15T21:57:59+00:00"
  },
  {
    "id": "51abfa9f2c16ac15",
    "product_id": "clickup",
    "product_name": "ClickUp",
    "icon_url": "https://www.google.com/s2/favicons?domain=clickup.com&sz=64",
    "title": "Introducing Super Agents™: The world’s first human-like AI agents",
    "link": "https://feedback.clickup.com/changelog/introducing-super-agents-the-worlds-first-human-like-ai-agents",
    "summary": "Today, we’re launching ClickUp Super Agents – the first human‑like AI agents that live inside ClickUp and collaborate with your team like real teammates.These aren’t just chatbots or one‑off automations. Super Agents:See your work the way you do: tasks, docs, chats, meetings, and schedules all in...",
    "date": "2025-12-22T17:30:47+00:00"
  },
  {
    "id": "8133574dc872869a",
    "product_id": "clickup",
    "product_name": "ClickUp",
    "icon_url": "https://www.google.com/s2/favicons?domain=clickup.com&sz=64",
    "title": "4.0 Release Notes Takeover",
    "link": "https://feedback.clickup.com/changelog/40-release-notes-takeover",
    "summary": "4.0: A New Era of Craft, Quality, and ConvergenceA new era starts today. ClickUp 4.0 is crafted from the ground up for perfect human productivity - Projects, Databases, Scheduling, Chats, DMs, Video Calls. And context is maximized, perfect for AI Agents' productivity. ✨ Effortless Navigation,...",
    "date": "2025-12-12T21:58:54+00:00"
  },
  {
    "id": "01fe930feaaa6a09",
    "product_id": "ems",
    "product_name": "EMS",
    "icon_url": "https://www.google.com/s2/favicons?domain=accruent.com&sz=64",
    "title": "upgrade",
    "link": "https://help.accruent.com/ems/Content/ReleaseNotes/2024%20Releases/Release%20Notes%202024.htm",
    "summary": "",
    "date": "2026-03-06T17:53:58.565738+00:00"
  },
  {
    "id": "7aba50c4d8071e11",
    "product_id": "ems",
    "product_name": "EMS",
    "icon_url": "https://www.google.com/s2/favicons?domain=accruent.com&sz=64",
    "title": "224.3.0",
    "link": "https://help.accruent.com/ems/Content/ReleaseNotes/2024%20Releases/Release%20Notes%202024.htm",
    "summary": "",
    "date": "2026-03-06T17:53:58.565789+00:00"
  },
  {
    "id": "e67335b00b3797c1",
    "product_id": "ems",
    "product_name": "EMS",
    "icon_url": "https://www.google.com/s2/favicons?domain=accruent.com&sz=64",
    "title": "224.2.0",
    "link": "https://help.accruent.com/ems/Content/ReleaseNotes/2024%20Releases/Release%20Notes%202024.htm",
    "summary": "",
    "date": "2026-03-06T17:53:58.565825+00:00"
  },
  {
    "id": "0d90b9c66b88bbce",
    "product_id": "ems",
    "product_name": "EMS",
    "icon_url": "https://www.google.com/s2/favicons?domain=accruent.com&sz=64",
    "title": "224.1.0",
    "link": "https://help.accruent.com/ems/Content/ReleaseNotes/2024%20Releases/Release%20Notes%202024.htm",
    "summary": "",
    "date": "2026-03-06T17:53:58.565857+00:00"
  },
  {
    "id": "6aa653e3e373f710",
    "product_id": "ems",
    "product_name": "EMS",
    "icon_url": "https://www.google.com/s2/favicons?domain=accruent.com&sz=64",
    "title": "223.3.0",
    "link": "https://help.accruent.com/ems/Content/ReleaseNotes/2024%20Releases/Release%20Notes%202024.htm",
    "summary": "",
    "date": "2026-03-06T17:53:58.565888+00:00"
  },
  {
    "id": "565b408be225300e",
    "product_id": "google-workspace",
    "product_name": "Google Workspace",
    "icon_url": "https://www.google.com/s2/favicons?domain=workspace.google.com&sz=64",
    "title": "Google Meet is now available on CarPlay",
    "link": "http://workspaceupdates.googleblog.com/2026/04/google-meet-is-now-available-on-carplay.html",
    "summary": "We’re excited to announce Google Meet for Apple CarPlay, allowing on-the-go professionals to stay connected hands-free and join meetings safely while on the road.With this update, users can now access Google Meet directly from their car's dashboard. This feature is designed to provide a seamless...",
    "date": "2026-04-02T16:50:00+00:00"
  },
  {
    "id": "31b4e888646cc1d5",
    "product_id": "google-workspace",
    "product_name": "Google Workspace",
    "icon_url": "https://www.google.com/s2/favicons?domain=workspace.google.com&sz=64",
    "title": "Export Google Vids directly to YouTube",
    "link": "http://workspaceupdates.googleblog.com/2026/04/export-google-vids-directly-to-youtube.html",
    "summary": "You can now publish the videos you create in Google Vids directly to YouTube. This saves you a few steps - previously you would export the project as an MP4 file, then go to YouTube to upload the file.Whether you are creating marketing videos, training materials, or educational content, this...",
    "date": "2026-04-02T16:13:00+00:00"
  },
  {
    "id": "94fe1664e074e1c6",
    "product_id": "google-workspace",
    "product_name": "Google Workspace",
    "icon_url": "https://www.google.com/s2/favicons?domain=workspace.google.com&sz=64",
    "title": "Record your screen directly from Chrome with the Google Vids Screen Recorder Chrome Extension",
    "link": "http://workspaceupdates.googleblog.com/2026/04/record-your-screen-directly-from-chrome-with-the-Google-Vids-Screen-Recorder-Chrome-Extension.html",
    "summary": "You can now quickly record your screen from any browser window using the new Google Vids Screen Recorder Chrome extension. Instead of having to open Google Vids to access recording functionality, you can now initiate a recording with a single click right from the Chrome extensions toolbar.This is...",
    "date": "2026-04-02T16:10:00+00:00"
  },
  {
    "id": "98659d064b3b908c",
    "product_id": "google-workspace",
    "product_name": "Google Workspace",
    "icon_url": "https://www.google.com/s2/favicons?domain=workspace.google.com&sz=64",
    "title": "Direct an avatar to speak and act anywhere with a consistent face and voice",
    "link": "http://workspaceupdates.googleblog.com/2026/04/direct-avatar-to-speak-and-act-anywhere-with-a-consistent-face-and-voice.html",
    "summary": "AI Avatars in Google Vids can deliver your message with a consistent face and voice throughout a video, and they are preferred 5x more often than those on other platforms.Today we’re excited to announce you can now place avatars in different scenes and have them interact with objects you specify,...",
    "date": "2026-04-02T16:06:00+00:00"
  },
  {
    "id": "5a8d2d279a236257",
    "product_id": "google-workspace",
    "product_name": "Google Workspace",
    "icon_url": "https://www.google.com/s2/favicons?domain=workspace.google.com&sz=64",
    "title": "Create and refine custom avatars in Google Vids",
    "link": "http://workspaceupdates.googleblog.com/2026/04/create-and-refine-custom-avatars-in-Google-Vids.html",
    "summary": "AI Avatars in Google Vids provide high-quality speakers preferred five times more often than those on other platforms. Now you can customize and refine these avatars to match your brand and message, with Nano Banana 2.Why use custom avatars?Unique Branding: Build an exclusive look that represents...",
    "date": "2026-04-02T16:03:00+00:00"
  },
  {
    "id": "f797e86c07e10880",
    "product_id": "korbyt",
    "product_name": "Korbyt",
    "icon_url": "https://www.google.com/s2/favicons?domain=gokorbyt.com&sz=64",
    "title": "Korbyt Anywhere Weekly Recap - 02.13.2026",
    "link": "https://product.korbyt.com/changelog/korbyt-anywhere-weekly-recap-02132026",
    "summary": "We're constantly working to improve Korbyt. Here's what we were up to this week: 🆕 New & Enhanced - Enhanced Proof of Play (POP) with **Hourly Reporting**, giving all customers more granular visibility into content performance throughout the day. - Improved Proof of Play to ensure reporting data...",
    "date": "2026-02-13T15:38:48+00:00"
  },
  {
    "id": "3ca2bd76a38407e8",
    "product_id": "korbyt",
    "product_name": "Korbyt",
    "icon_url": "https://www.google.com/s2/favicons?domain=gokorbyt.com&sz=64",
    "title": "Korbyt Booking V9.7.1",
    "link": "https://product.korbyt.com/changelog/korbyt-booking-v971",
    "summary": "# What’s New? ## Deep Link to Locate Colleague on Floorplan (Bookit) Implemented a deep link capability in Bookit that enables authenticated users to directly locate a colleague’s booked space on the floorplan via a URL and book near them. ### Key Functionality **Hyperlink Integration** • The...",
    "date": "2026-02-12T09:05:29+00:00"
  },
  {
    "id": "3f5b910c597cabb5",
    "product_id": "korbyt",
    "product_name": "Korbyt",
    "icon_url": "https://www.google.com/s2/favicons?domain=gokorbyt.com&sz=64",
    "title": "Korbyt Anywhere Product Recap - 01.12.2026",
    "link": "https://product.korbyt.com/changelog/korbyt-anywhere-product-recap-01122026",
    "summary": "We're constantly working to improve Korbyt. Here's what we were up to over the break and last week week: 🆕 New & Enhanced - **Secrets API: Credential Management** — IT Admins can now securely manage the lifecycle of API credentials using a centralized Secrets API. This includes creating, listing,...",
    "date": "2026-01-12T16:36:21+00:00"
  },
  {
    "id": "ceaabe1754b3907a",
    "product_id": "korbyt",
    "product_name": "Korbyt",
    "icon_url": "https://www.google.com/s2/favicons?domain=gokorbyt.com&sz=64",
    "title": "Korbyt Anywhere Release Recap - 12.05.2025",
    "link": "https://product.korbyt.com/changelog/korbyt-anywhere-release-recap-12052025",
    "summary": "We're constantly working to improve Korbyt. Here's what we were up to this week: 🐞 Squashed Bugs - Fixed an issue where YouTube element showed an error due to recent changes in YouTube's Terms of Service. - Resolved a styling inheritance issue in Korbyt Create AI Layouts where elements did not...",
    "date": "2025-12-05T15:05:58+00:00"
  },
  {
    "id": "8f69cdb419c85fe3",
    "product_id": "kuali-build",
    "product_name": "Kuali Build",
    "icon_url": "https://www.google.com/s2/favicons?domain=kuali.com&sz=64",
    "title": "New: Hierarchical Group Selection in Data Lookup Gadgets",
    "link": "https://announcekit.app/kuali/announcements/new-hierarchical-group-selection-in-data-lookup-gadgets-1VYPrq",
    "summary": "You can now select Groups from within your organizational blueprint hierarchy in a single lookup. Form designers can enable a new setting—...",
    "date": "2026-04-06T17:25:00+00:00"
  },
  {
    "id": "80762f228c0d3a19",
    "product_id": "kuali-build",
    "product_name": "Kuali Build",
    "icon_url": "https://www.google.com/s2/favicons?domain=kuali.com&sz=64",
    "title": "UPDATE: Updates to How Table Gadget Data is Returned Via API (now scheduled for April 19, 2026)",
    "link": "https://announcekit.app/kuali/announcements/update-updates-to-how-table-gadget-data-is-returned-via-api-now-scheduled-for-april-19-2026-2kXwT6",
    "summary": "We’re postponing updates to how Table gadget data is formatted in API JSON responses (see the original announcement for details). To allow a...",
    "date": "2026-04-03T16:50:15+00:00"
  },
  {
    "id": "2eb9937ddce09c94",
    "product_id": "kuali-build",
    "product_name": "Kuali Build",
    "icon_url": "https://www.google.com/s2/favicons?domain=kuali.com&sz=64",
    "title": "Coming Soon: Updates to How Table Gadget Data is Returned Via API",
    "link": "https://announcekit.app/kuali/announcements/coming-soon-updates-to-how-table-gadget-data-is-returned-via-api-4o7y6Y",
    "summary": "We wanted to make you aware of forthcoming changes to how our Table gadget data is formatted in JSON when returned via the API. If you have ...",
    "date": "2026-04-01T21:39:18+00:00"
  },
  {
    "id": "f34a2aae004f5696",
    "product_id": "kuali-build",
    "product_name": "Kuali Build",
    "icon_url": "https://www.google.com/s2/favicons?domain=kuali.com&sz=64",
    "title": "Coming Soon: Streamlined UI updates - Preview Now!",
    "link": "https://announcekit.app/kuali/announcements/coming-soon-streamlined-ui-updates---preview-now-3SeYz6",
    "summary": "We’re rolling out a set of user interface updates designed to streamline your experience and give you more flexibility when working in a for...",
    "date": "2026-03-31T20:00:00+00:00"
  },
  {
    "id": "b3d51cb140e150ca",
    "product_id": "kuali-build",
    "product_name": "Kuali Build",
    "icon_url": "https://www.google.com/s2/favicons?domain=kuali.com&sz=64",
    "title": "New: Form Outline Download",
    "link": "https://announcekit.app/kuali/announcements/new-form-outline-download-2pu0M0",
    "summary": "You can now download a complete, review-ready outline of your form directly from the form designer (either the saved Draft or Published vers...",
    "date": "2026-03-25T22:00:00+00:00"
  },
  {
    "id": "fd15db8a53a19f10",
    "product_id": "macos",
    "product_name": "macOS",
    "icon_url": "https://www.google.com/s2/favicons?domain=apple.com&sz=64",
    "title": "macOS 26.5 beta (25F5042g)",
    "link": "https://developer.apple.com/news/releases/?id=03302026c",
    "summary": "View downloadsView release notes",
    "date": "2026-03-30T17:00:00+00:00"
  },
  {
    "id": "8f2885091136ab69",
    "product_id": "microsoft-office",
    "product_name": "Microsoft Office",
    "icon_url": "https://www.google.com/s2/favicons?domain=office.com&sz=64",
    "title": "Security Updates for Microsoft 365 Apps Releases",
    "link": "https://learn.microsoft.com/en-us/officeupdates/release-notes-microsoft365-apps",
    "summary": "For a complete list of security updates, see the following article:",
    "date": "2026-03-06T17:54:07.627266+00:00"
  },
  {
    "id": "b9360485c3e61f3c",
    "product_id": "microsoft-office",
    "product_name": "Microsoft Office",
    "icon_url": "https://www.google.com/s2/favicons?domain=office.com&sz=64",
    "title": "History for Microsoft 365 Apps Releases",
    "link": "https://learn.microsoft.com/en-us/officeupdates/release-notes-microsoft365-apps",
    "summary": "For a complete list of releases and the supported versions for each channel, see the following article:",
    "date": "2026-03-06T17:54:07.627389+00:00"
  },
  {
    "id": "185d4d7625c4f74e",
    "product_id": "microsoft-office",
    "product_name": "Microsoft Office",
    "icon_url": "https://www.google.com/s2/favicons?domain=office.com&sz=64",
    "title": "Download Sizes for Microsoft 365 Apps Releases",
    "link": "https://learn.microsoft.com/en-us/officeupdates/release-notes-microsoft365-apps",
    "summary": "For a complete list of update releases sizes, see the following article:",
    "date": "2026-03-06T17:54:07.627508+00:00"
  },
  {
    "id": "813b1ad089721490",
    "product_id": "microsoft-office",
    "product_name": "Microsoft Office",
    "icon_url": "https://www.google.com/s2/favicons?domain=office.com&sz=64",
    "title": "Release Notes for Microsoft 365 Apps Releases",
    "link": "https://learn.microsoft.com/en-us/officeupdates/release-notes-microsoft365-apps",
    "summary": "For a complete list of release notes by update channel and year, see the following articles:",
    "date": "2026-03-06T17:54:07.627609+00:00"
  },
  {
    "id": "324fe31ac188c1d9",
    "product_id": "microsoft-office",
    "product_name": "Microsoft Office",
    "icon_url": "https://www.google.com/s2/favicons?domain=office.com&sz=64",
    "title": "Release Notes for Microsoft 365 Insiders",
    "link": "https://learn.microsoft.com/en-us/officeupdates/release-notes-microsoft365-apps",
    "summary": "For a complete list of release notes for Insiders, see the following articles:",
    "date": "2026-03-06T17:54:07.627705+00:00"
  },
  {
    "id": "e6eed6c1344b6f68",
    "product_id": "ninjaone",
    "product_name": "NinjaOne",
    "icon_url": "https://www.google.com/s2/favicons?domain=ninjaone.com&sz=64",
    "title": "Gain Better IT Asset Control and Visibility into Software Licensing With NinjaOne 13.0",
    "link": "https://www.ninjaone.com/blog/gain-visibility-with-ninjaone-13/",
    "summary": "NinjaOne’s 13.0 release advances IT asset management (ITAM) capabilities with software license improvements that offer greater cost visibility, usage history for custom licenses, and refined control over permissions and assignments. The platform now includes robust Lost Mode support for managed...",
    "date": "2026-03-31T14:00:45+00:00"
  },
  {
    "id": "4861482635a84858",
    "product_id": "ninjaone",
    "product_name": "NinjaOne",
    "icon_url": "https://www.google.com/s2/favicons?domain=ninjaone.com&sz=64",
    "title": "Unify IT Service, Assets, and Operations With NinjaOne 12.0",
    "link": "https://www.ninjaone.com/blog/unify-it-with-ninjaone-12-0/",
    "summary": "Release Schedule: January 27 – February 25 NinjaOne’s 12.0 release has arrived to improve how IT teams manage assets, integrate service delivery with business operations, gain insights into profitability and health status, and proactively resolve any recovery issues. MSPs can now sync service...",
    "date": "2026-02-09T14:00:23+00:00"
  },
  {
    "id": "4c648a6b3f65d207",
    "product_id": "papercut",
    "product_name": "PaperCut",
    "icon_url": "https://www.google.com/s2/favicons?domain=papercut.com&sz=64",
    "title": "25.0.10",
    "link": "https://www.papercut.com/products/mf/release-history/25-0/",
    "summary": "Important upgrade information Version 25 includes significant updates, which may introduce breaking changes, new internet connection requirements, and mandatory updates for some optional components.Upgrading from version 24.x? Please review Important points to know about PaperCut MF version...",
    "date": "2026-03-31T00:00:00+00:00"
  },
  {
    "id": "29b118fba425721c",
    "product_id": "papercut",
    "product_name": "PaperCut",
    "icon_url": "https://www.google.com/s2/favicons?domain=papercut.com&sz=64",
    "title": "25.0.9",
    "link": "https://www.papercut.com/products/mf/release-history/25-0/",
    "summary": "Important upgrade information Version 25 includes significant updates, which may introduce breaking changes, new internet connection requirements, and mandatory updates for some optional components.Upgrading from version 24.x? Please review Important points to know about PaperCut MF version...",
    "date": "2026-03-26T00:00:00+00:00"
  },
  {
    "id": "3a81a7e4205a54f5",
    "product_id": "papercut",
    "product_name": "PaperCut",
    "icon_url": "https://www.google.com/s2/favicons?domain=papercut.com&sz=64",
    "title": "25.0.8",
    "link": "https://www.papercut.com/products/mf/release-history/25-0/",
    "summary": "Important upgrade information Version 25 includes significant updates, which may introduce breaking changes, new internet connection requirements, and mandatory updates for some optional components.Upgrading from version 24.x? Please review Important points to know about PaperCut MF version...",
    "date": "2026-02-10T00:00:00+00:00"
  },
  {
    "id": "14378e3d42e688d0",
    "product_id": "papercut",
    "product_name": "PaperCut",
    "icon_url": "https://www.google.com/s2/favicons?domain=papercut.com&sz=64",
    "title": "25.0.6",
    "link": "https://www.papercut.com/products/mf/release-history/25-0/",
    "summary": "Important upgrade information Version 25 includes significant updates, which may introduce breaking changes, new internet connection requirements, and mandatory updates for some optional components.Upgrading from version 24.x? Please review Important points to know about PaperCut MF version...",
    "date": "2025-11-25T00:00:00+00:00"
  },
  {
    "id": "d815a5971e1aa4e6",
    "product_id": "papercut",
    "product_name": "PaperCut",
    "icon_url": "https://www.google.com/s2/favicons?domain=papercut.com&sz=64",
    "title": "25.0.5",
    "link": "https://www.papercut.com/products/mf/release-history/25-0/",
    "summary": "Important upgrade information Version 25 includes significant updates, which may introduce breaking changes, new internet connection requirements, and mandatory updates for some optional components.Upgrading from version 24.x? Please review Important points to know about PaperCut MF version...",
    "date": "2025-10-28T00:00:00+00:00"
  },
  {
    "id": "06a1b6a05e1c3232",
    "product_id": "screencloud",
    "product_name": "ScreenCloud",
    "icon_url": "https://www.google.com/s2/favicons?domain=screencloud.com&sz=64",
    "title": "4.11.2",
    "link": "https://help.screencloud.com/en/articles/10120269-screencloud-player-software-changelogs",
    "summary": "New: Support for Amazon’s Remote Device Management (RDM) for Signage Sticks, including:Screen/TV mute and unmute via HDMI-CECScreen/TV power on and off via HDMI-CECDevice rebootScreenshot and full-screen captureDeep cache clearing (player app and Android system cache)Player app restartCPU and GPU...",
    "date": "January 23, 2026"
  },
  {
    "id": "e1dab31261398830",
    "product_id": "screencloud",
    "product_name": "ScreenCloud",
    "icon_url": "https://www.google.com/s2/favicons?domain=screencloud.com&sz=64",
    "title": "4.9.0",
    "link": "https://help.screencloud.com/en/articles/10120269-screencloud-player-software-changelogs",
    "summary": "New: Amazon Signage Stick (ASS) dedicated player. Previously ran Amazon Fire OS player on ASS device.",
    "date": "May 8, 2025"
  },
  {
    "id": "25cbe092cc1d040f",
    "product_id": "screencloud",
    "product_name": "ScreenCloud",
    "icon_url": "https://www.google.com/s2/favicons?domain=screencloud.com&sz=64",
    "title": "4.7.16",
    "link": "https://help.screencloud.com/en/articles/10120269-screencloud-player-software-changelogs",
    "summary": "Rollback release fixing issues introduced in v4.7.12. Released at 50% for Fire OS players alongside v4.6.30.",
    "date": "March 28, 2024"
  },
  {
    "id": "5e682909839a6ae1",
    "product_id": "scribe",
    "product_name": "Scribe",
    "icon_url": "https://www.google.com/s2/favicons?domain=scribehow.com&sz=64",
    "title": "Document Import turns existing docs into usable Scribes",
    "link": "https://www.launchnotes.com/powered-by?company=ScribeHow&utm_campaign=https%3A%2F%2Fscribe.launchnotes.io%2F&utm_content=project-release-index&utm_medium=powered-by&utm_source=in-app",
    "summary": "Loading... Loading...",
    "date": "March 31, 2026"
  },
  {
    "id": "6df6cff416b50286",
    "product_id": "scribe",
    "product_name": "Scribe",
    "icon_url": "https://www.google.com/s2/favicons?domain=scribehow.com&sz=64",
    "title": "Document Import turns existing docs into usable Scribes",
    "link": "https://scribe.launchnotes.io/announcements/document-import-turns-existing-docs-into-usable-scribes",
    "summary": "Loading...",
    "date": "March 31, 2026"
  },
  {
    "id": "51db2b716d22e25d",
    "product_id": "scribe",
    "product_name": "Scribe",
    "icon_url": "https://www.google.com/s2/favicons?domain=scribehow.com&sz=64",
    "title": "Pro Pro Team Enterprise",
    "link": "https://scribe.launchnotes.io/",
    "summary": "",
    "date": "2026-03-31T20:20:40.625180+00:00"
  },
  {
    "id": "c85468d03abbc92b",
    "product_id": "scribe",
    "product_name": "Scribe",
    "icon_url": "https://www.google.com/s2/favicons?domain=scribehow.com&sz=64",
    "title": "Document Import turns existing docs into usable Scribes",
    "link": "https://scribe.launchnotes.io/",
    "summary": "",
    "date": "2026-03-31T20:20:40.625197+00:00"
  },
  {
    "id": "a202083b037a806a",
    "product_id": "slack",
    "product_name": "Slack",
    "icon_url": "https://www.google.com/s2/favicons?domain=slack.com&sz=64",
    "title": "PKCE is now generally available!",
    "link": "https://docs.slack.dev/changelog/2026/03/30/pkce",
    "summary": "We are excited to announce support for Proof Key for Code Exchange (PKCE). PKCE is an OAuth security extension that enables developers to build more secure Slack applications on public clients, such as desktop apps and mobile apps, without the need to embed a vulnerable client_secret.",
    "date": "2026-03-30T00:00:00+00:00"
  },
  {
    "id": "75ea88db7f495000",
    "product_id": "slack",
    "product_name": "Slack",
    "icon_url": "https://www.google.com/s2/favicons?domain=slack.com&sz=64",
    "title": "Release: Slack CLI v3.15.0",
    "link": "https://docs.slack.dev/changelog/2026/03/19/slack-cli",
    "summary": "Version 3.15.0 of the developer tools for the Slack platform has arrived!",
    "date": "2026-03-19T00:00:00+00:00"
  },
  {
    "id": "544e979428ac6810",
    "product_id": "slack",
    "product_name": "Slack",
    "icon_url": "https://www.google.com/s2/favicons?domain=slack.com&sz=64",
    "title": "Optional scopes have landed",
    "link": "https://docs.slack.dev/changelog/2026/03/16/optional-scopes",
    "summary": "You can now mark individual OAuth scopes as optional when configuring your Slack app! Optional scopes give users more control over what data your app can access during installation, without blocking them from installing your app entirely.",
    "date": "2026-03-16T00:00:00+00:00"
  },
  {
    "id": "97a112bfc59de73a",
    "product_id": "slack",
    "product_name": "Slack",
    "icon_url": "https://www.google.com/s2/favicons?domain=slack.com&sz=64",
    "title": "New supported markdown types for rich text in Block Kit",
    "link": "https://docs.slack.dev/changelog/2026/03/06/block-kit-rich-text",
    "summary": "The following new supported markdown types for rich text when using Block Kit in your apps are being rolled out:",
    "date": "2026-03-06T00:00:00+00:00"
  },
  {
    "id": "c58291813e7015df",
    "product_id": "slack",
    "product_name": "Slack",
    "icon_url": "https://www.google.com/s2/favicons?domain=slack.com&sz=64",
    "title": "Set status method scope update",
    "link": "https://docs.slack.dev/changelog/2026/03/05/set-status-scope-update",
    "summary": "The assistant.threads.setStatus API method now accepts either the assistantwrite scope. This allows channel-based apps to use AI loading states in channels, without having to request assistantwrite scope in favor of the chat:write scope exclusively, so update your app soon!",
    "date": "2026-03-05T00:00:00+00:00"
  },
  {
    "id": "d04afd8189d29908",
    "product_id": "smartdeploy",
    "product_name": "SmartDeploy",
    "icon_url": "https://www.google.com/s2/favicons?domain=smartdeploy.com&sz=64",
    "title": "What's new in SmartDeploy release 3.0.1060",
    "link": "https://www.smartdeploy.com/blog/new-release-smartdeploy-301060",
    "summary": "",
    "date": "2023-02-23T00:00-07:00"
  },
  {
    "id": "f3178e95c4d034d4",
    "product_id": "smartdeploy",
    "product_name": "SmartDeploy",
    "icon_url": "https://www.google.com/s2/favicons?domain=smartdeploy.com&sz=64",
    "title": "New Release: SmartDeploy 3.0.1050",
    "link": "https://www.smartdeploy.com/blog/new-release-smartdeploy-301050",
    "summary": "",
    "date": "2022-10-20T00:00-06:00"
  },
  {
    "id": "b53f08061e093898",
    "product_id": "smartdeploy",
    "product_name": "SmartDeploy",
    "icon_url": "https://www.google.com/s2/favicons?domain=smartdeploy.com&sz=64",
    "title": "Just launched: Windows patching functionality (and more!)",
    "link": "https://www.smartdeploy.com/blog/just-launched-windows-patching",
    "summary": "",
    "date": "2022-05-18T00:00-06:00"
  },
  {
    "id": "5e48da512d8b17c1",
    "product_id": "smartdeploy",
    "product_name": "SmartDeploy",
    "icon_url": "https://www.google.com/s2/favicons?domain=smartdeploy.com&sz=64",
    "title": "New Release: SmartDeploy 3.0.1030, Software Asset Management",
    "link": "https://www.smartdeploy.com/blog/new-release-smartdeploy-3-0-1030-software-asset-management",
    "summary": "",
    "date": "2022-02-01T00:00-06:00"
  },
  {
    "id": "a1d2c1d6a50eeb16",
    "product_id": "smartdeploy",
    "product_name": "SmartDeploy",
    "icon_url": "https://www.google.com/s2/favicons?domain=smartdeploy.com&sz=64",
    "title": "Press Release: PDQ.com Acquires SmartDeploy",
    "link": "https://www.smartdeploy.com/blog/press-release-pdq-com-acquires-smartdeploy",
    "summary": "",
    "date": "2022-01-25T00:00-06:00"
  },
  {
    "id": "f3e45ac525b4a384",
    "product_id": "windows",
    "product_name": "Windows",
    "icon_url": "https://www.google.com/s2/favicons?domain=microsoft.com&sz=64",
    "title": "Announcing Windows 11 Insider Preview Build 28020.1803 (Canary Channel)",
    "link": "https://blogs.windows.com/windows-insider/2026/04/03/announcing-windows-11-insider-preview-build-28020-1803-canary-channel/",
    "summary": "Hello Windows Insiders, today we are releasing Windows 11 Insider Preview Build 28020.1803 to the Canary Channel. (KB 5083824) What’s new in Canary Build 28020.1803 Changes and Improvements g The post Announcing Windows 11 Insider Preview Build 28020.1803 (Canary Channel) appeared first on Windows...",
    "date": "2026-04-03T17:07:21+00:00"
  },
  {
    "id": "9c637d154d42ca2c",
    "product_id": "windows",
    "product_name": "Windows",
    "icon_url": "https://www.google.com/s2/favicons?domain=microsoft.com&sz=64",
    "title": "Announcing Windows 11 Insider Preview Build for Canary Channel 29560.1000",
    "link": "https://blogs.windows.com/windows-insider/2026/04/03/announcing-windows-11-insider-preview-build-for-canary-channel-29560-1000/",
    "summary": "Hello Windows Insiders, today we’re releasing Windows Insider Preview Build 29560.1000 to the Windows 11 Insider Canary Channel on the optional 29500 build series. What’s new in Canary Build 29560.1000 Change The post Announcing Windows 11 Insider Preview Build for Canary Channel 29560.1000...",
    "date": "2026-04-03T17:07:07+00:00"
  },
  {
    "id": "a718addd96c8f9b4",
    "product_id": "windows",
    "product_name": "Windows",
    "icon_url": "https://www.google.com/s2/favicons?domain=microsoft.com&sz=64",
    "title": "Announcing Windows 11 Insider Preview Build 26300.8155 (Dev Channel)",
    "link": "https://blogs.windows.com/windows-insider/2026/04/03/announcing-windows-11-insider-preview-build-26300-8155-dev-channel/",
    "summary": "Hello Windows Insiders, today we are releasing Windows 11 Insider Preview Build 26300.8155 (KB 5083822) to the Dev Channel. Changes in Dev Channel builds and updates are documented in two buckets: new features, and improvements (inc The post Announcing Windows 11 Insider Preview Build 26300.8155...",
    "date": "2026-04-03T17:05:18+00:00"
  },
  {
    "id": "fbc09e254f3cced9",
    "product_id": "windows",
    "product_name": "Windows",
    "icon_url": "https://www.google.com/s2/favicons?domain=microsoft.com&sz=64",
    "title": "Announcing Windows 11 Insider Preview Build 26220.8148 (Beta Channel)",
    "link": "https://blogs.windows.com/windows-insider/2026/04/03/announcing-windows-11-insider-preview-build-26220-8148-beta-channel/",
    "summary": "Hello Windows Insiders, today we are releasing Windows 11 Insider Preview Build 26220.8148 (KB 5083825) to the Beta Channel. Changes in Beta Channel builds and updates are documented in two buckets: new features, and improvements (i The post Announcing Windows 11 Insider Preview Build 26220.8148...",
    "date": "2026-04-03T17:05:02+00:00"
  },
  {
    "id": "33fd4036cd788581",
    "product_id": "windows",
    "product_name": "Windows",
    "icon_url": "https://www.google.com/s2/favicons?domain=microsoft.com&sz=64",
    "title": "Announcing Windows 11 Insider Preview Build for Canary Channel 29558.1000",
    "link": "https://blogs.windows.com/windows-insider/2026/03/30/announcing-windows-11-insider-preview-build-for-canary-channel-29558-1000/",
    "summary": "Hello Windows Insiders, today we’re releasing Windows Insider Preview Build 29558.1000 to the Windows 11 Insider Canary Channel on the optional 29500 build series. What’s new in Canary Build 29558.1000 Change The post Announcing Windows 11 Insider Preview Build for Canary Channel 29558.1000...",
    "date": "2026-03-30T21:06:04+00:00"
  },
  {
    "id": "bb9b1c389efaf659",
    "product_id": "zoom",
    "product_name": "Zoom",
    "icon_url": "https://www.google.com/s2/favicons?domain=zoom.us&sz=64",
    "title": "Phone API endpoint deprecations",
    "link": "https://developers.zoom.us/changelog/phone/phone-api-endpoint-deprecations",
    "summary": "Tags: breaking-change, deprecation | Zoom deprecated several endpoints for phone numbers, plans, cloud peering, SMS campaigns, and related settings. Use the new Number Management APIs for enhanced, streamlined management. Migrate by **June 30, 2026**. We will not support deprecated endpoints after...",
    "date": "2026-04-02T00:00:00+00:00"
  },
  {
    "id": "92f9b3973444bb77",
    "product_id": "zoom",
    "product_name": "Zoom",
    "icon_url": "https://www.google.com/s2/favicons?domain=zoom.us&sz=64",
    "title": "Version 1.0.4",
    "link": "https://developers.zoom.us/changelog/probe-sdk/javascript/1.0.4",
    "summary": "Tags: bug-fix, sdk-version | New diagnostic tools for screen sharing and camera troubleshooting, including APIs to detect environment issues, permission errors, and black screens, with real-time progress updates and privacy safeguards. New error codes, expanded test coverage, refactored user-agent...",
    "date": "2026-04-02T00:00:00+00:00"
  },
  {
    "id": "f4d8953eb059b908",
    "product_id": "zoom",
    "product_name": "Zoom",
    "icon_url": "https://www.google.com/s2/favicons?domain=zoom.us&sz=64",
    "title": "New session AI interpreter usage summary webhook",
    "link": "https://developers.zoom.us/changelog/video-sdk/april-02-2026",
    "summary": "Tags: api-release | New session AI interpreter usage summary webhook.",
    "date": "2026-04-02T00:00:00+00:00"
  },
  {
    "id": "6540b83dccba92b7",
    "product_id": "zoom",
    "product_name": "Zoom",
    "icon_url": "https://www.google.com/s2/favicons?domain=zoom.us&sz=64",
    "title": "Added new rc_reason response field for Dashboards API endpoints",
    "link": "https://developers.zoom.us/changelog/accounts/march-30-2026",
    "summary": "Tags: api-release | Added rc_response field for Dashboards quality of service API endpoints.",
    "date": "2026-03-30T00:00:00+00:00"
  },
  {
    "id": "22bb1c5747afb5ed",
    "product_id": "zoom",
    "product_name": "Zoom",
    "icon_url": "https://www.google.com/s2/favicons?domain=zoom.us&sz=64",
    "title": "Version 5.3.0",
    "link": "https://developers.zoom.us/changelog/contact-center/android/5.3.0",
    "summary": "Tags: bug-fix, new-feature, sdk-version | Added Hindi localization support; add support for toggling consumer cameras off or on; add support for left-right split screen in landscape orientation; upgrade Android version.",
    "date": "2026-03-30T00:00:00+00:00"
  },
  {
    "id": "02c742af723aa7ae",
    "product_id": "kuali-build",
    "product_name": "Kuali Build",
    "icon_url": "https://www.google.com/s2/favicons?domain=kuali.com&sz=64",
    "title": "New: Read Only Gadgets and Default Values",
    "link": "https://announcekit.app/kuali/announcements/new-read-only-gadgets-and-default-values-2T0iiI",
    "summary": "You can now control how data is set and edited in your forms with new Read-only and Default Value configurations. This makes it easier to su...",
    "date": "2026-03-24T19:55:00+00:00"
  },
  {
    "id": "f68fad5be0bbb964",
    "product_id": "kuali-build",
    "product_name": "Kuali Build",
    "icon_url": "https://www.google.com/s2/favicons?domain=kuali.com&sz=64",
    "title": "February 2026 Release Announcement",
    "link": "https://announcekit.app/kuali/announcements/february-2026-release-announcement-4w3LEI",
    "summary": "Feature Enhanced Logic for Conditional Visibility and Branch Workflow - We've added the ability to do All of the Below or Some of the Below...",
    "date": "2026-03-23T17:01:34+00:00"
  },
  {
    "id": "b8f349ea880e5cd6",
    "product_id": "windows",
    "product_name": "Windows",
    "icon_url": "https://www.google.com/s2/favicons?domain=microsoft.com&sz=64",
    "title": "Announcing Windows 11 Insider Preview Build 28020.1797 (Canary Channel)",
    "link": "https://blogs.windows.com/windows-insider/2026/03/30/announcing-windows-11-insider-preview-build-28020-1797-canary-channel/",
    "summary": "Hello Windows Insiders, today we are releasing Windows 11 Insider Preview Build 28020.1797 to the Canary Channel. (KB 5079490) What’s new in Canary Build 28020.1797 Changes and Improvements g The post Announcing Windows 11 Insider Preview Build 28020.1797 (Canary Channel) appeared first on Windows...",
    "date": "2026-03-30T21:05:51+00:00"
  },
  {
    "id": "032861e26462393d",
    "product_id": "windows",
    "product_name": "Windows",
    "icon_url": "https://www.google.com/s2/favicons?domain=microsoft.com&sz=64",
    "title": "Announcing Windows 11 Insider Preview Build 26300.8142 (Dev Channel)",
    "link": "https://blogs.windows.com/windows-insider/2026/03/30/announcing-windows-11-insider-preview-build-26300-8142-dev-channel/",
    "summary": "Hello Windows Insiders, today we are releasing Windows 11 Insider Preview Build 26300.8142 (KB 5079492 The post Announcing Windows 11 Insider Preview Build 26300.8142 (Dev Channel) appeared first on Windows Insider Blog.",
    "date": "2026-03-30T21:04:17+00:00"
  },
  {
    "id": "5169fd66e0a56a02",
    "product_id": "windows",
    "product_name": "Windows",
    "icon_url": "https://www.google.com/s2/favicons?domain=microsoft.com&sz=64",
    "title": "Announcing Windows 11 Insider Preview Build 26220.8138 (Beta Channel)",
    "link": "https://blogs.windows.com/windows-insider/2026/03/30/announcing-windows-11-insider-preview-build-26220-8138-beta-channel/",
    "summary": "Hello Windows Insiders, today we are releasing Windows 11 Insider Preview Build 26220.8138 (KB 5079491< The post Announcing Windows 11 Insider Preview Build 26220.8138 (Beta Channel) appeared first on Windows Insider Blog.",
    "date": "2026-03-30T09:05:21+00:00"
  },
  {
    "id": "3e2571f90a54dec5",
    "product_id": "windows",
    "product_name": "Windows",
    "icon_url": "https://www.google.com/s2/favicons?domain=microsoft.com&sz=64",
    "title": "Announcing Windows 11 Insider Preview Build for Canary Channel 29553.1000",
    "link": "https://blogs.windows.com/windows-insider/2026/03/20/announcing-windows-11-insider-preview-build-for-canary-channel-29553-1000/",
    "summary": "Hello Windows Insiders, today we’re releasing Windows Insider Preview Build 29553.1000 to the Windows 11 Insider Canary Channel on the optional 29500 build series. What’s new in Canary Build 29553.1000 Change The post Announcing Windows 11 Insider Preview Build for Canary Channel 29553.1000...",
    "date": "2026-03-20T17:06:13+00:00"
  },
  {
    "id": "58952b3e54ec169a",
    "product_id": "zoom",
    "product_name": "Zoom",
    "icon_url": "https://www.google.com/s2/favicons?domain=zoom.us&sz=64",
    "title": "Version 5.3.0",
    "link": "https://developers.zoom.us/changelog/contact-center/ios/5.3.0",
    "summary": "Tags: bug-fix, new-feature, sdk-version | Added Hindi localization support; add support for toggling consumer cameras off or on; add support for left-right split screen in landscape orientation.",
    "date": "2026-03-30T00:00:00+00:00"
  },
  {
    "id": "8ec025a0f5720994",
    "product_id": "zoom",
    "product_name": "Zoom",
    "icon_url": "https://www.google.com/s2/favicons?domain=zoom.us&sz=64",
    "title": "New endpoint for Export API",
    "link": "https://developers.zoom.us/changelog/docs/march-30-2026",
    "summary": "Tags: api-release | Added new Export API.",
    "date": "2026-03-30T00:00:00+00:00"
  },
  {
    "id": "20b3bac6280b1ee2",
    "product_id": "zoom",
    "product_name": "Zoom",
    "icon_url": "https://www.google.com/s2/favicons?domain=zoom.us&sz=64",
    "title": "RTMS March release",
    "link": "https://developers.zoom.us/changelog/rtms/rtms-march-release",
    "summary": "Tags: new-feature | Add RTMS integration with Zoom Contact Center, a reorganized audio parameters matrix, single individual video stream subscription, stream closure requests, and media-socket timeout extension.",
    "date": "2026-03-30T00:00:00+00:00"
  },
  {
    "id": "93db0bf88d692c5e",
    "product_id": "zoom",
    "product_name": "Zoom",
    "icon_url": "https://www.google.com/s2/favicons?domain=zoom.us&sz=64",
    "title": "Version 7.0.0",
    "link": "https://developers.zoom.us/changelog/zoom-rooms-controller/android/7.0.0",
    "summary": "Tags: new-feature, sdk-version | This initial Android ZRCSDK release introduces the first public SDK surface for Zoom Rooms, including SDK initialization, room pairing, pre-meeting workflows, meeting lifecycle, audio/video/sharing controls, participant management, recording, reminders, and room...",
    "date": "2026-03-30T00:00:00+00:00"
  },
  {
    "id": "d45c1c894460171d",
    "product_id": "google-workspace",
    "product_name": "Google Workspace",
    "icon_url": "https://www.google.com/s2/favicons?domain=workspace.google.com&sz=64",
    "title": "Upcoming change to default setting for downloading Google Meet recordings",
    "link": "http://workspaceupdates.googleblog.com/2026/03/upcoming-change-to-default-setting-for-downloading-Google-Meet-recordings.html",
    "summary": "Currently, Google Meet video recordings do not allow viewers to download or copy them by default unless the recording owner explicitly allows it. As a result, the \"Ask Gemini\" functionality within the Drive viewer is also disabled by default for viewers who aren’t file owners.Starting April 30,...",
    "date": "2026-04-01T18:42:00+00:00"
  },
  {
    "id": "462517d4a537a06c",
    "product_id": "google-workspace",
    "product_name": "Google Workspace",
    "icon_url": "https://www.google.com/s2/favicons?domain=workspace.google.com&sz=64",
    "title": "Form creation with Gemini and more now available in more languages",
    "link": "http://workspaceupdates.googleblog.com/2026/04/form-creation-with-gemini-and-more-now-available-in-more-languages.html",
    "summary": "Last year, we announced Help me create in Google Forms and then expanded access to the feature to seven more languages.Help me create in Google Forms drafts your questions 3x faster than doing it manually.*Now, this feature is also available to users in 21 more languages including Arabic, Catalan,...",
    "date": "2026-04-01T17:32:00+00:00"
  },
  {
    "id": "2533894b4313a680",
    "product_id": "google-workspace",
    "product_name": "Google Workspace",
    "icon_url": "https://www.google.com/s2/favicons?domain=workspace.google.com&sz=64",
    "title": "Generate beautiful and editable slides with ease in Google Slides",
    "link": "http://workspaceupdates.googleblog.com/2026/04/enerate-beautiful-and-editable-slides-with-ease-in-Google-Slides.html",
    "summary": "Slide generation just got a major upgrade. Gemini can now create fully editable, brand-matched slides using dynamic layouts tailored to your specific content. To ensure visual consistency, Gemini securely analyzes your existing deck to generate designs that fit your established style. You can also...",
    "date": "2026-04-01T17:27:00+00:00"
  },
  {
    "id": "17e2f3fcbf8557a1",
    "product_id": "google-workspace",
    "product_name": "Google Workspace",
    "icon_url": "https://www.google.com/s2/favicons?domain=workspace.google.com&sz=64",
    "title": "An update on secondary calendar lifecycle changes and a new API",
    "link": "http://workspaceupdates.googleblog.com/2026/03/an-update-on-secondary-calendar-lifecycle-changes-and-a-new-API.html",
    "summary": "We recently announced a change to the ownership model of secondary calendars to improve data governance. As part of this, we emailed impacted customers to let them know that orphan secondary calendars would be deleted starting on April 27, 2026.Since that announcement, we’ve received valuable...",
    "date": "2026-03-30T20:18:00+00:00"
  },
  {
    "id": "b21fbaa10077df93",
    "product_id": "google-workspace",
    "product_name": "Google Workspace",
    "icon_url": "https://www.google.com/s2/favicons?domain=workspace.google.com&sz=64",
    "title": "Download the third-party attestation for data regions",
    "link": "http://workspaceupdates.googleblog.com/2026/03/download-third-party-attestation-for-data-regions.html",
    "summary": "Beginning today, admins have access to an independent review of Google Workspace’s data regions, not only for their compliance needs but also for their peace of mind.This external evaluation from Coalfire, a third-party assessment organization, gives Assured Controls customers the confidence that...",
    "date": "2026-03-30T18:20:00+00:00"
  },
  {
    "id": "eadece1cc263b0fe",
    "product_id": "kuali-build",
    "product_name": "Kuali Build",
    "icon_url": "https://www.google.com/s2/favicons?domain=kuali.com&sz=64",
    "title": "New Associations Gadget!",
    "link": "https://announcekit.app/kuali/announcements/new-associations-gadget-3zEwAU",
    "summary": "Users often need visibility into how documents are connected across the system. The new Associations gadget provides a clear view of all do...",
    "date": "2026-03-23T16:35:00+00:00"
  },
  {
    "id": "adeebde5119ce43c",
    "product_id": "google-workspace",
    "product_name": "Google Workspace",
    "icon_url": "https://www.google.com/s2/favicons?domain=workspace.google.com&sz=64",
    "title": "Ransomware detection and file restoration for Google Drive now generally available",
    "link": "http://workspaceupdates.googleblog.com/2026/03/ransomware-detection-and-file-restoration-for-Google-Drive-now-generally-available.html",
    "summary": "In September 2025, we launched ransomware detection and file restoration in beta to help organizations minimize the impact of malware attacks on personal computers. Today, we’re excited to share these two features are generally available with significant improvements in malware detection.Compared...",
    "date": "2026-03-30T18:15:00+00:00"
  },
  {
    "id": "693ccfb409db0ecb",
    "product_id": "google-workspace",
    "product_name": "Google Workspace",
    "icon_url": "https://www.google.com/s2/favicons?domain=workspace.google.com&sz=64",
    "title": "Introducing guest accounts: Collaborate securely and communicate with non-Workspace users in Google Chat",
    "link": "http://workspaceupdates.googleblog.com/2026/03/introducing-guest-accounts.html",
    "summary": "Today, we're excited to announce the general availability of guest accounts in Google Workspace. Guest accounts empower organizations to securely collaborate with customers, partners, and vendors that are not on Google Workspace. More than secure, real-time messaging in Google Chat, guest accounts...",
    "date": "2026-03-30T18:07:00+00:00"
  },
  {
    "id": "27b74afa43a8a94e",
    "product_id": "google-workspace",
    "product_name": "Google Workspace",
    "icon_url": "https://www.google.com/s2/favicons?domain=workspace.google.com&sz=64",
    "title": "Google Workspace Updates Weekly Recap - March 27, 2026",
    "link": "http://workspaceupdates.googleblog.com/2026/03/weekly-recap-03-27-2026.html",
    "summary": "Safeguarded guest admit flow in Google MeetThe new safeguarded guest admit flow assists hosts in meetings when they respond to users who ask to join meetings (also known as ”knocking”). This makes it easier for hosts to handle large volumes of requests and helps reduce the attention and time...",
    "date": "2026-03-27T20:28:00+00:00"
  },
  {
    "id": "1d53d2762cd2ff4f",
    "product_id": "kuali-build",
    "product_name": "Kuali Build",
    "icon_url": "https://www.google.com/s2/favicons?domain=kuali.com&sz=64",
    "title": "New: Extended Person Fields",
    "link": "https://announcekit.app/kuali/announcements/new-extended-person-fields-1Rp2Y8",
    "summary": "We’ve enhanced the Person record with new fields to better support institutional needs. You can now manage richer user metadata and use it i...",
    "date": "2026-03-09T16:15:00+00:00"
  },
  {
    "id": "8549143880d4f8f9",
    "product_id": "scribe",
    "product_name": "Scribe",
    "icon_url": "https://www.google.com/s2/favicons?domain=scribehow.com&sz=64",
    "title": "Pin guides anywhere on a webpage",
    "link": "https://www.launchnotes.com/powered-by?company=ScribeHow&utm_campaign=https%3A%2F%2Fscribe.launchnotes.io%2F&utm_content=project-release-index&utm_medium=powered-by&utm_source=in-app",
    "summary": "Loading... Loading...",
    "date": "March 25, 2026"
  },
  {
    "id": "123ccc408fdbad82",
    "product_id": "scribe",
    "product_name": "Scribe",
    "icon_url": "https://www.google.com/s2/favicons?domain=scribehow.com&sz=64",
    "title": "Pin guides anywhere on a webpage",
    "link": "https://scribe.launchnotes.io/announcements/pin-guides-anywhere-on-a-webpage",
    "summary": "Loading...",
    "date": "March 25, 2026"
  },
  {
    "id": "27bfc6f072bded52",
    "product_id": "scribe",
    "product_name": "Scribe",
    "icon_url": "https://www.google.com/s2/favicons?domain=scribehow.com&sz=64",
    "title": "Enterprise Viewing",
    "link": "https://scribe.launchnotes.io/",
    "summary": "",
    "date": "2026-03-25T00:44:21.648082+00:00"
  },
  {
    "id": "5ae9ebfd943800f9",
    "product_id": "scribe",
    "product_name": "Scribe",
    "icon_url": "https://www.google.com/s2/favicons?domain=scribehow.com&sz=64",
    "title": "Pin guides anywhere on a webpage",
    "link": "https://scribe.launchnotes.io/",
    "summary": "",
    "date": "2026-03-25T00:44:21.648102+00:00"
  }
]